MANIFEST.in
README.md
setup.py
search/__init__.py
search/search.py
search/search_gui.py
search_cli.egg-info/PKG-INFO
search_cli.egg-info/SOURCES.txt
search_cli.egg-info/dependency_links.txt
search_cli.egg-info/entry_points.txt
search_cli.egg-info/requires.txt
search_cli.egg-info/top_level.txt